split_query/__init__.py
split_query/__version__.py
split_query/cache.py
split_query/decorators.py
split_query/engine.py
split_query/extract.py
split_query/interface.py
split_query/core/__init__.py
split_query/core/domain.py
split_query/core/expand.py
split_query/core/expressions.py
split_query/core/logic.py
split_query/core/serialise.py
split_query/core/wrappers.py
split_query-0.2.2.dist-info/DESCRIPTION.rst
split_query-0.2.2.dist-info/METADATA
split_query-0.2.2.dist-info/RECORD
split_query-0.2.2.dist-info/WHEEL
split_query-0.2.2.dist-info/metadata.json
split_query-0.2.2.dist-info/top_level.txt
